json2daisy/__init__.py
json2daisy/__main__.py
json2daisy/json2daisy.py
json2daisy/resources/LICENSE
json2daisy/resources/component_defs.json
json2daisy/resources/component_defs_patchsm.json
json2daisy/resources/component_defs_petalsm.json
json2daisy/resources/field.json
json2daisy/resources/patch.json
json2daisy/resources/patch_init.json
json2daisy/resources/petal.json
json2daisy/resources/petal_125b_sm.json
json2daisy/resources/pod.json
json2daisy/templates/daisy.h
wstd2daisy-0.5.3.dist-info/LICENSE
wstd2daisy-0.5.3.dist-info/METADATA
wstd2daisy-0.5.3.dist-info/WHEEL
wstd2daisy-0.5.3.dist-info/top_level.txt
wstd2daisy-0.5.3.dist-info/RECORD
