Metadata-Version: 2.1
Name: wstd2daisy
Version: 0.5.3
Summary: A utility for generating Daisy board support files from JSON descriptions
Home-page: https://github.com/electro-smith/json2daisy
Author: Electrosmith
Author-email: shensley@electro-smith.com
License: MIT
Project-URL: Bug Tracker, https://github.com/electro-smith/json2daisy/issues
Classifier: Programming Language :: Python :: 3
Classifier: License :: OSI Approved :: MIT License
Classifier: Operating System :: OS Independent
Classifier: Programming Language :: Python :: 3.8
Classifier: Programming Language :: Python :: 3.9
Classifier: Programming Language :: Python :: 3.10
Classifier: Programming Language :: Python :: 3.11
Classifier: Programming Language :: Python :: 3.12
Requires-Python: >=3.8
License-File: LICENSE
Requires-Dist: Jinja2>=2.11
Requires-Dist: importlib-resources; python_version == "3.8"
